.coveragerc
AUTHORS.rst
CHANGES.rst
CONTRIBUTING.rst
INSTALL.rst
LICENSE
MANIFEST.in
Procfile
README.md
README.rst
RELEASE-NOTES.rst
babel.ini
gunicorn.cfg
pytest.ini
requirements-devel.txt
run-tests.sh
setup.cfg
setup.py
beard_server/__init__.py
beard_server/app.py
beard_server/celery.py
beard_server/config.py
beard_server/ext.py
beard_server/tasks.py
beard_server/version.py
beard_server/views.py
beard_server.egg-info/PKG-INFO
beard_server.egg-info/SOURCES.txt
beard_server.egg-info/dependency_links.txt
beard_server.egg-info/not-zip-safe
beard_server.egg-info/requires.txt
beard_server.egg-info/top_level.txt
beard_server/modules/__init__.py
beard_server/modules/clustering/__init__.py
beard_server/modules/clustering/beard.py
beard_server/modules/clustering/recid.py
beard_server/modules/clustering/resolver.py
beard_server/modules/clustering/views.py
beard_server/modules/clustering/classifiers/ethnicity_estimator.pickle
beard_server/modules/clustering/classifiers/linkage.dat
beard_server/modules/clustering/utils/__init__.py
beard_server/modules/clustering/utils/beard_clustering.py
beard_server/modules/clustering/utils/beard_distance.py
beard_server/modules/clustering/utils/beard_sampling.py
beard_server/modules/clustering/utils/beard_utils.py
beard_server/modules/matching/__init__.py
beard_server/modules/matching/match.py
beard_server/modules/matching/simplex.py
beard_server/modules/matching/subproblems.py
beard_server/modules/predictor/__init__.py
beard_server/modules/predictor/arxiv.py
beard_server/modules/predictor/views.py
beard_server/modules/predictor/classifiers/linkage.dat
beard_server/modules/text/__init__.py
beard_server/modules/text/utils.py
beard_server/modules/text/views.py
beard_server/static/css/beard.css
beard_server/static/img/background.jpg
beard_server/static/img/logo.png
beard_server/static/js/app.js
beard_server/templates/base.html
beard_server/templates/index.html
docs/Makefile
docs/api.rst
docs/authors.rst
docs/changes.rst
docs/conf.py
docs/contributing.rst
docs/index.rst
docs/installation.rst
docs/license.rst
docs/make.bat
docs/usage.rst
examples/app.py
tests/conftest.py
tests/test_beard_server.py
tests/test_celery.py
tests/clustering/test_beard.py
