Metadata-Version: 1.1
Name: beard-server
Version: 0.3.0
Summary: Beard as RESTful API and Celery service.
Home-page: https://github.com/inspirehep/beard-server
Author: CERN
Author-email: admin@inspirehep.net
License: GPLv2
Keywords: author disambiguation
Platform: any
Classifier: Environment :: Web Environment
Classifier: Intended Audience :: Developers
Classifier: License :: OSI Approved :: GNU General Public License v2 (GPLv2)
Classifier: Operating System :: OS Independent
Classifier: Programming Language :: Python
Classifier: Programming Language :: Python :: 2
Classifier: Programming Language :: Python :: 2.7
Classifier: Development Status :: 4 - Beta
Classifier: Topic :: Scientific/Engineering :: Artificial Intelligence
Classifier: Topic :: Scientific/Engineering :: Information Analysis
